README.md
setup.cfg
setup.py
LMSQuery.egg-info/PKG-INFO
LMSQuery.egg-info/SOURCES.txt
LMSQuery.egg-info/dependency_links.txt
LMSQuery.egg-info/requires.txt
LMSQuery.egg-info/top_level.txt
lmsquery/__init__.py
lmsquery/const.py
lmsquery/lmsquery.py