Metadata-Version: 1.1
Name: LMSQuery
Version: 0.4.1
Summary: Query library for Logitech Media Server
Home-page: https://github.com/roberteinhaus/lmsquery
Author: Robert Einhaus
Author-email: robert@einhaus.info
License: MIT
Keywords: logitech media server lms
Platform: UNKNOWN
Classifier: Development Status :: 5 - Production/Stable
Classifier: Environment :: Console
Classifier: Intended Audience :: Developers
Classifier: License :: OSI Approved :: MIT License
Classifier: Operating System :: OS Independent
Classifier: Programming Language :: Python
Classifier: Topic :: Software Development
Classifier: Topic :: Software Development :: Libraries
Classifier: Topic :: Software Development :: Libraries :: Python Modules
